jparse/__init__.py
jparse/jparse.py
jparse-0.1.8.dist-info/DESCRIPTION.rst
jparse-0.1.8.dist-info/METADATA
jparse-0.1.8.dist-info/RECORD
jparse-0.1.8.dist-info/WHEEL
jparse-0.1.8.dist-info/metadata.json
jparse-0.1.8.dist-info/top_level.txt
