Metadata-Version: 2.0
Name: jparse
Version: 0.1.8
Summary: A JSON-like object parsing tool for python
Home-page: https://github.com/elisong/jparse
Author: Eli Song
Author-email: elisong.ah@gmail.com
License: Apache 2.0
Keywords: python json parser
Platform: Posix; MacOS X; Windows
Classifier: Development Status :: 3 - Alpha
Classifier: Intended Audience :: Developers
Classifier: Topic :: Utilities
Classifier: License :: OSI Approved :: Apache Software License
Classifier: Programming Language :: Python :: 2.7
Classifier: Programming Language :: Python :: 3.4
Classifier: Programming Language :: Python :: 3.5
Classifier: Programming Language :: Python :: 3.6
Requires-Python: >=2.7
Requires-Dist: pandas
